tests/__init__.py
tests/test_all.py
tests/test_cnh.py
tests/test_cnpj.py
tests/test_cns.py
tests/test_cpf.py
tests/test_generic.py
tests/test_pis.py
tests/test_titulo_eleitor.py
validate_docbr/BaseDoc.py
validate_docbr/CNH.py
validate_docbr/CNPJ.py
validate_docbr/CNS.py
validate_docbr/CPF.py
validate_docbr/PIS.py
validate_docbr/TituloEleitoral.py
validate_docbr/__init__.py
validate_docbr/generic.py
validate_docbr-1.8.1.dist-info/LICENSE
validate_docbr-1.8.1.dist-info/METADATA
validate_docbr-1.8.1.dist-info/WHEEL
validate_docbr-1.8.1.dist-info/top_level.txt
validate_docbr-1.8.1.dist-info/RECORD
