Metadata-Version: 2.1
Name: validate-docbr
Version: 1.8.1
Summary: Validate brazilian documents.
Home-page: https://github.com/alvarofpp/validate-docbr
Author: Álvaro Ferreira Pires de Paiva
Author-email: alvarofepipa@gmail.com
License: UNKNOWN
Platform: UNKNOWN
Classifier: Programming Language :: Python :: 3
Classifier: License :: OSI Approved :: MIT License
Classifier: Operating System :: OS Independent
